{
  "id": "MAP_POKEMON_TOWER_6F",
  "name": "PokemonTower_6F",
  "layout": "LAYOUT_POKEMON_TOWER_6F",
  "music": "MUS_RG_POKE_TOWER",
  "region_map_section": "MAPSEC_POKEMON_TOWER",
  "requires_flash": false,
  "weather": "WEATHER_FOG_HORIZONTAL",
  "map_type": "MAP_TYPE_INDOOR",
  "allow_cycling": false,
  "allow_escaping": true,
  "allow_running": false,
  "show_map_name": true,
  "battle_scene": "MAP_BATTLE_SCENE_NORMAL",
  "connections": 0,
  "object_events": [
    {
      "graphics_id": "OBJ_EVENT_GFX_ITEM_BALL",
      "in_connection": false,
      "x": 15,
      "y": 15,
      "elevation": 3,
      "movement_type": "MOVEMENT_TYPE_FACE_DOWN",
      "movement_range_x": 1,
      "movement_range_y": 1,
      "trainer_type": "TRAINER_TYPE_NONE",
      "trainer_sight_or_berry_tree_id": "0",
      "script": "PokemonTower_6F_EventScript_ItemXAccuracy",
      "flag": "FLAG_HIDE_POKEMON_TOWER_6F_X_ACCURACY"
    },
    {
      "graphics_id": "OBJ_EVENT_GFX_ITEM_BALL",
      "in_connection": false,
      "x": 5,
      "y": 15,
      "elevation": 3,
      "movement_type": "MOVEMENT_TYPE_FACE_DOWN",
      "movement_range_x": 1,
      "movement_range_y": 1,
      "trainer_type": "TRAINER_TYPE_NONE",
      "trainer_sight_or_berry_tree_id": "0",
      "script": "PokemonTower_6F_EventScript_ItemRareCandy",
      "flag": "FLAG_HIDE_POKEMON_TOWER_6F_RARE_CANDY"
    },
    {
      "graphics_id": "OBJ_EVENT_GFX_CHANNELER",
      "in_connection": false,
      "x": 13,
      "y": 10,
      "elevation": 3,
      "movement_type": "MOVEMENT_TYPE_FACE_RIGHT",
      "movement_range_x": 1,
      "movement_range_y": 1,
      "trainer_type": "TRAINER_TYPE_NORMAL",
      "trainer_sight_or_berry_tree_id": "3",
      "script": "PokemonTower_6F_EventScript_Angelica",
      "flag": "0"
    },
    {
      "graphics_id": "OBJ_EVENT_GFX_CHANNELER",
      "in_connection": false,
      "x": 18,
      "y": 6,
      "elevation": 3,
      "movement_type": "MOVEMENT_TYPE_FACE_LEFT",
      "movement_range_x": 1,
      "movement_range_y": 1,
      "trainer_type": "TRAINER_TYPE_NORMAL",
      "trainer_sight_or_berry_tree_id": "3",
      "script": "PokemonTower_6F_EventScript_Jennifer",
      "flag": "0"
    },
    {
      "graphics_id": "OBJ_EVENT_GFX_CHANNELER",
      "in_connection": false,
      "x": 9,
      "y": 6,
      "elevation": 3,
      "movement_type": "MOVEMENT_TYPE_FACE_DOWN",
      "movement_range_x": 1,
      "movement_range_y": 1,
      "trainer_type": "TRAINER_TYPE_NORMAL",
      "trainer_sight_or_berry_tree_id": "3",
      "script": "PokemonTower_6F_EventScript_Emilia",
      "flag": "0"
    },
    {
      "graphics_id": "OBJ_EVENT_GFX_CUBONE",
      "in_connection": false,
      "x": 5,
      "y": 9,
      "elevation": 3,
      "movement_type": "MOVEMENT_TYPE_FACE_DOWN",
      "movement_range_x": 0,
      "movement_range_y": 0,
      "trainer_type": "TRAINER_TYPE_NONE",
      "trainer_sight_or_berry_tree_id": "0",
      "script": "NULL",
      "flag": "FLAG_HIDE_POKEMON_TOWER_CUBONE"
    },
    {
      "graphics_id": "OBJ_EVENT_GFX_MAROWAK_GHOST",
      "in_connection": false,
      "x": 10,
      "y": 16,
      "elevation": 3,
      "movement_type": "MOVEMENT_TYPE_FACE_RIGHT",
      "movement_range_x": 0,
      "movement_range_y": 0,
      "trainer_type": "TRAINER_TYPE_NONE",
      "trainer_sight_or_berry_tree_id": "0",
      "script": "NULL",
      "flag": "FLAG_HIDE_POKEMON_TOWER_MAROWAK"
    },
    {
      "graphics_id": "OBJ_EVENT_GFX_OLD_AMBER",
      "in_connection": false,
      "x": 3,
      "y": 14,
      "elevation": 3,
      "movement_type": "MOVEMENT_TYPE_NONE",
      "movement_range_x": 0,
      "movement_range_y": 0,
      "trainer_type": "TRAINER_TYPE_NONE",
      "trainer_sight_or_berry_tree_id": "0",
      "script": "PokemonTower_6F_EventScript_Gengarite",
      "flag": "FLAG_HIDE_GENGARITE"
    }
  ],
  "warp_events": [
    {
      "x": 18,
      "y": 10,
      "elevation": 0,
      "dest_map": "MAP_POKEMON_TOWER_5F",
      "dest_warp_id": 1
    },
    {
      "x": 11,
      "y": 16,
      "elevation": 0,
      "dest_map": "MAP_POKEMON_TOWER_7F",
      "dest_warp_id": 0
    }
  ],
  "coord_events": [
    {
      "type": "trigger",
      "x": 11,
      "y": 15,
      "elevation": 3,
      "var": "VAR_POKEMON_TOWER_STATE",
      "var_value": "1",
      "script": "PokemonTower_6F_EventScript_GhostTriggerLeft"
    },
    {
      "type": "trigger",
      "x": 12,
      "y": 15,
      "elevation": 3,
      "var": "VAR_POKEMON_TOWER_STATE",
      "var_value": "1",
      "script": "PokemonTower_6F_EventScript_GhostTriggerRight"
    }
  ],
  "bg_events": [

  ],
  "floor_number": ""
}
